psocket/__init__.py
psocket-1.0.9.dist-info/LICENSE
psocket-1.0.9.dist-info/METADATA
psocket-1.0.9.dist-info/WHEEL
psocket-1.0.9.dist-info/top_level.txt
psocket-1.0.9.dist-info/RECORD
