Metadata-Version: 2.1
Name: psocket
Version: 1.0.9
Summary: The cross-platform tool to work with remote connection using sockets
Home-page: https://github.com/c-pher/PSocket.git
Author: Andrey Komissarov
Author-email: a.komisssarov@gmail.com
License: MIT
Classifier: Programming Language :: Python :: 3
Classifier: License :: OSI Approved :: MIT License
Classifier: Operating System :: OS Independent
Classifier: Intended Audience :: System Administrators
Classifier: Intended Audience :: Developers
Classifier: Natural Language :: English
Classifier: Programming Language :: Python :: 3.6
Classifier: Topic :: System :: Systems Administration
Classifier: Topic :: Software Development :: Libraries :: Python Modules
Requires-Python: >=3.6
License-File: LICENSE
Requires-Dist: plogger (>=1.0.6)
